random_username_for_pip_package_toadharvard.cpython-310-x86_64-linux-gnu.so
random_username_for_pip_package_toadharvard-1.0.0.dist-info/METADATA
random_username_for_pip_package_toadharvard-1.0.0.dist-info/WHEEL
random_username_for_pip_package_toadharvard-1.0.0.dist-info/entry_points.txt
random_username_for_pip_package_toadharvard-1.0.0.dist-info/licenses/COPYING
random_username_for_pip_package_toadharvard-1.0.0.dist-info/RECORD
