Metadata-Version: 2.1
Name: random_username_for_pip_package_toadharvard
Version: 1.0.0
Summary: Python bindings for Desbordante: https://github.com/Mstrutov/Desbordante
License: AGPL-3.0-only
Requires-Python: >=3.7
License-File: COPYING
